umap/__init__.py
umap/distances.py
umap/nndescent.py
umap/rp_tree.py
umap/sparse.py
umap/spectral.py
umap/umap_.py
umap/utils.py
umap/validation.py
umap_learn_modified-0.3.8.dist-info/LICENSE.txt
umap_learn_modified-0.3.8.dist-info/METADATA
umap_learn_modified-0.3.8.dist-info/WHEEL
umap_learn_modified-0.3.8.dist-info/top_level.txt
umap_learn_modified-0.3.8.dist-info/RECORD
