Metadata-Version: 1.2
Name: umap-learn-modified
Version: 0.3.8
Summary: Forked from umap-learn (https://github.com/lmcinnes/umap). Change API so that UMAP accepts precomputed KNN input, rather than always calculating by itself. Remove numba.njit parallel option to avoid delay in the cloud.
Home-page: https://github.com/lilab-bcb/umap
Maintainer: Bo Li
Maintainer-email: bli28@mgh.harvard.edu
License: BSD
Keywords: dimension reduction t-sne manifold
Platform: UNKNOWN
Classifier: Development Status :: 3 - Alpha
Classifier: Intended Audience :: Science/Research
Classifier: Intended Audience :: Developers
Classifier: License :: OSI Approved
Classifier: Programming Language :: C
Classifier: Programming Language :: Python
Classifier: Topic :: Software Development
Classifier: Topic :: Scientific/Engineering
Classifier: Operating System :: Microsoft :: Windows
Classifier: Operating System :: POSIX
Classifier: Operating System :: Unix
Classifier: Operating System :: MacOS
Classifier: Programming Language :: Python :: 2.7
Classifier: Programming Language :: Python :: 3.6
